{
  "TranslationProperties": {
    "Name": "server.items.Slumbering_Metal_Legs.name"
  },
  "Quality": "Uncommon",
  "ItemLevel": 20,
  "PlayerAnimationsId": "Block",
  "ItemSoundSetId": "ISS_Armor_Heavy",
  "Categories": [
    "Items.Armors"
  ],
  "Icon": "Icons/ItemsGenerated/Armor_Slumbering_Metal_Legs.png",
  "Model": "Items/Armors/Slumbering_Metal/Legs.blockymodel",
  "Texture": "Items/Armors/Slumbering_Metal/Legs_Texture.png",
  "Recipe": {
    "Input": [
      {
        "ItemId": "Metal_Slumbering",
        "Quantity": 13
      },
      {
        "ItemId": "Ingredient_Leather_Light",
        "Quantity": 6
      },
      {
        "ItemId": "Carbon_Fiber_Scrap",
        "Quantity": 4
      }
    ],
    "BenchRequirement": [
      {
        "Id": "Armor_Bench",
        "Type": "Crafting",
        "Categories": [
          "Armor_Legs"
        ]
      }
    ],
    "KnowledgeRequired": false,
    "TimeSeconds": 3
  },
  "Interactions": {
    "Primary": {
      "Interactions": [
        {
          "Type": "EquipItem"
        }
      ]
    },
    "Secondary": {
      "Interactions": [
        {
          "Type": "EquipItem"
        }
      ]
    }
  },
  "Armor": {
    "ArmorSlot": "Legs",
    "BaseDamageResistance": 0,
    "CosmeticsToHide": [
      "Pants",
      "Shoes"
    ],
    "DamageResistance": {
      "Physical": [
        {
          "Amount": 0.07,
          "CalculationType": "Multiplicative"
        }
      ],
      "Projectile": [
        {
          "Amount": 0.07,
          "CalculationType": "Multiplicative"
        }
      ]
    },
    "StatModifiers": {
      "Health": [
        {
          "Amount": 13,
          "CalculationType": "Additive"
        }
      ]
    }
  },
  "MaxDurability": 100,
  "DurabilityLossOnHit": 0.5,
  "Tags": {
    "Type": [
      "Armor"
    ],
    "Family": [
      "Iron"
    ]
  },
  "IconProperties": {
    "Scale": 0.5,
    "Rotation": [
      22.5,
      45,
      22.5
    ],
    "Translation": [
      0,
      -25.8
    ]
  }
}
